cropy/__init__.py
cropy/entropy.py
cropy-0.3.data/scripts/cropy
cropy-0.3.dist-info/METADATA
cropy-0.3.dist-info/WHEEL
cropy-0.3.dist-info/top_level.txt
cropy-0.3.dist-info/RECORD
