Metadata-Version: 2.1
Name: cropy
Version: 0.3
Summary: Command line tool and module to crop an image to a specific resolution removing less important parts first
Home-page: https://github.com/mapado/cropy
Author: Jerry Nieuviarts
Author-email: jerry@mapado.com
License: FreeBSD
Keywords: image,crop,entropy,autocrop,resize
Platform: UNKNOWN
Classifier: Development Status :: 3 - Alpha
Classifier: Environment :: Console
Classifier: Intended Audience :: Developers
Classifier: License :: OSI Approved :: BSD License
Classifier: Natural Language :: English
Classifier: Operating System :: POSIX :: Linux
Classifier: Operating System :: Unix
Classifier: Operating System :: MacOS :: MacOS X
Classifier: Programming Language :: Python :: 2.6
Classifier: Programming Language :: Python :: 2.7
Classifier: Topic :: Scientific/Engineering :: Artificial Intelligence
Requires-Dist: numpy
Requires-Dist: scipy
Requires-Dist: scikit-image
Requires-Dist: Pillow
